[
    {
       "model": "workout_app.workout",
       "pk": 1,
       "fields": {
          "weekly_frequency": 3,
          "type_of_workout": "Strength",
          "workout_name": "Upper Body Strength",
          "tracker_id": 1
       }
    },
    {
       "model": "workout_app.workout",
       "pk": 2,
       "fields": {
          "weekly_frequency": 4,
          "type_of_workout": "Cardio",
          "workout_name": "Running Endurance",
          "tracker_id": 1
       }
    },
    {
       "model": "workout_app.workout",
       "pk": 3,
       "fields": {
          "weekly_frequency": 5,
          "type_of_workout": "HIIT",
          "workout_name": "Full Body HIIT",
          "tracker_id": 2
       }
    },
    {
       "model": "workout_app.workout",
       "pk": 4,
       "fields": {
          "weekly_frequency": 2,
          "type_of_workout": "Yoga",
          "workout_name": "Morning Yoga",
          "tracker_id": 2
       }
    },
    {
       "model": "workout_app.workout",
       "pk": 5,
       "fields": {
          "weekly_frequency": 4,
          "type_of_workout": "Strength",
          "workout_name": "Lower Body Strength",
          "tracker_id": 3
       }
    },
    {
       "model": "workout_app.workout",
       "pk": 6,
       "fields": {
          "weekly_frequency": 3,
          "type_of_workout": "Cardio",
          "workout_name": "Cycling",
          "tracker_id": 3
       }
    },
    {
       "model": "workout_app.workout",
       "pk": 7,
       "fields": {
          "weekly_frequency": 5,
          "type_of_workout": "Yoga",
          "workout_name": "Evening Stretch",
          "tracker_id": 4
       }
    },
    {
       "model": "workout_app.workout",
       "pk": 8,
       "fields": {
          "weekly_frequency": 3,
          "type_of_workout": "Strength",
          "workout_name": "Push-Pull Strength",
          "tracker_id": 4
       }
    },
    {
       "model": "workout_app.workout",
       "pk": 9,
       "fields": {
          "weekly_frequency": 2,
          "type_of_workout": "Cardio",
          "workout_name": "Jump Rope",
          "tracker_id": 5
       }
    },
    {
       "model": "workout_app.workout",
       "pk": 10,
       "fields": {
          "weekly_frequency": 4,
          "type_of_workout": "HIIT",
          "workout_name": "Tabata Workout",
          "tracker_id": 5
       }
    }
 ]
 